llama_index/readers/azcognitive_search/__init__.py
llama_index/readers/azcognitive_search/base.py
llama_index_readers_azcognitive_search-0.4.1.dist-info/METADATA
llama_index_readers_azcognitive_search-0.4.1.dist-info/WHEEL
llama_index_readers_azcognitive_search-0.4.1.dist-info/licenses/LICENSE
llama_index_readers_azcognitive_search-0.4.1.dist-info/RECORD
