Metadata-Version: 2.4
Name: llama-index-readers-azcognitive-search
Version: 0.4.1
Summary: llama-index readers azcognitive_search integration
Author-email: Your Name <you@example.com>
Maintainer: mrcabellom
License-Expression: MIT
License-File: LICENSE
Requires-Python: <4.0,>=3.9
Requires-Dist: azure-identity<2,>=1.15.0
Requires-Dist: azure-search-documents<12,>=11.4.0
Requires-Dist: llama-index-core<0.15,>=0.13.0
